docs/spi_master.v
module spi_master #(
    parameter CLK_DIV = 4
)(
    input        clk,
    input        rst,
    input        start,
    input  [7:0] tx_data,
    input        miso,

    output reg [7:0] rx_data,
    output reg       busy,
    output reg       done,
    output reg       mosi,
    output reg       sclk,
    output reg       cs
);

    reg [7:0] tx_shift;
    reg [7:0] rx_shift;
    reg [3:0] bit_count;
    reg [15:0] clk_count;

    always @(posedge clk or posedge rst) begin
        if (rst) begin
            rx_data  <= 8'b0;
            tx_shift <= 8'b0;
            rx_shift <= 8'b0;
            bit_count <= 4'b0;
            clk_count <= 16'b0;
            busy <= 1'b0;
            done <= 1'b0;
            mosi <= 1'b0;
            sclk <= 1'b0;
            cs <= 1'b1;
        end
        else begin
            done <= 1'b0;

            if (!busy) begin
                sclk <= 1'b0;
                cs <= 1'b1;

                if (start) begin
                    busy <= 1'b1;
                    cs <= 1'b0;
                    tx_shift <= tx_data;
                    rx_shift <= 8'b0;
                    bit_count <= 4'd0;
                    clk_count <= 16'd0;
                    mosi <= tx_data[7];
                end
            end
            else begin
                if (clk_count == CLK_DIV - 1) begin
                    clk_count <= 16'd0;
                    sclk <= ~sclk;

                    if (sclk == 1'b0) begin
                        // Rising edge: sample MISO
                        rx_shift <= {rx_shift[6:0], miso};
                    end
                    else begin
                        // Falling edge: change MOSI
                        if (bit_count == 4'd7) begin
                            rx_data <= rx_shift;
                            busy <= 1'b0;
                            done <= 1'b1;
                            cs <= 1'b1;
                            mosi <= 1'b0;
                            sclk <= 1'b0;
                        end
                        else begin
                            bit_count <= bit_count + 1'b1;
                            tx_shift <= {tx_shift[6:0], 1'b0};
                            mosi <= tx_shift[6];
                        end
                    end
                end
                else begin
                    clk_count <= clk_count + 1'b1;
                end
            end
        end
    end

endmodule

simulation/tb_spi_master.v
`timescale 1ns/1ps

module tb_spi_master;

    reg clk;
    reg rst;
    reg start;
    reg [7:0] tx_data;
    reg miso;

    wire [7:0] rx_data;
    wire busy;
    wire done;
    wire mosi;
    wire sclk;
    wire cs;

    reg [7:0] slave_data;
    integer i;

    spi_master #(
        .CLK_DIV(4)
    ) uut (
        .clk(clk),
        .rst(rst),
        .start(start),
        .tx_data(tx_data),
        .miso(miso),
        .rx_data(rx_data),
        .busy(busy),
        .done(done),
        .mosi(mosi),
        .sclk(sclk),
        .cs(cs)
    );

    always #5 clk = ~clk;

    initial begin
        clk = 0;
        rst = 1;
        start = 0;
        tx_data = 8'b10110010;
        miso = 0;
        slave_data = 8'b11001101;

        #20;
        rst = 0;

        #20;

        // Put first slave bit on MISO before first SCLK rising edge
        miso = slave_data[7];

        start = 1;
        #10;
        start = 0;

        // Change MISO after every falling edge
        for (i = 0; i < 7; i = i + 1) begin
            @(negedge sclk);
            slave_data = {slave_data[6:0], 1'b0};
            miso = slave_data[7];
        end

        // Wait until transfer completes
        @(posedge done);

        #1;

        $display("====================================");
        $display("       SPI MASTER SIMULATION");
        $display("====================================");
        $display("TX DATA = %b", tx_data);
        $display("RX DATA = %b", rx_data);
        $display("BUSY    = %b", busy);
        $display("DONE    = %b", done);
        $display("====================================");

        if (rx_data == 8'b11001101)
            $display("TEST RESULT = PASS");
        else
            $display("TEST RESULT = FAIL");

        #20;
        $finish;
    end

    initial begin
        $dumpfile("simulation/spi_master.vcd");
        $dumpvars(0, tb_spi_master);
    end

endmodule

simulation/spi_master.vcd
$date
	Thu Oct  8 18:02:58 2026
$end
$version
	Icarus Verilog
$end
$timescale
	1ps
$end
$scope module tb_spi_master $end
$var wire 1 ! sclk $end
$var wire 8 " rx_data [7:0] $end
$var wire 1 # mosi $end
$var wire 1 $ done $end
$var wire 1 % cs $end
$var wire 1 & busy $end
$var reg 1 ' clk $end
$var reg 1 ( miso $end
$var reg 1 ) rst $end
$var reg 8 * slave_data [7:0] $end
$var reg 1 + start $end
$var reg 8 , tx_data [7:0] $end
$var integer 32 - i [31:0] $end
$scope module uut $end
$var wire 1 ' clk $end
$var wire 1 ( miso $end
$var wire 1 ) rst $end
$var wire 1 + start $end
$var wire 8 . tx_data [7:0] $end
$var parameter 32 / CLK_DIV $end
$var reg 4 0 bit_count [3:0] $end
$var reg 1 & busy $end
$var reg 16 1 clk_count [15:0] $end
$var reg 1 % cs $end
$var reg 1 $ done $end
$var reg 1 # mosi $end
$var reg 8 2 rx_data [7:0] $end
$var reg 8 3 rx_shift [7:0] $end
$var reg 1 ! sclk $end
$var reg 8 4 tx_shift [7:0] $end
$upscope $end
$upscope $end
$enddefinitions $end
$comment Show the parameter values. $end
$dumpall
b100 /
$end
#0
$dumpvars
b0 4
b0 3
b0 2
b0 1
b0 0
b10110010 .
bx -
b10110010 ,
0+
b11001101 *
1)
0(
0'
0&
1%
0$
0#
b0 "
0!
$end
#5000
1'
#10000
0'
#15000
1'
#20000
0'
0)
#25000
1'
#30000
0'
#35000
1'
#40000
0'
1+
1(
#45000
1#
b10110010 4
0%
1&
1'
#50000
0'
b0 -
0+
#55000
b1 1
1'
#60000
0'
#65000
b10 1
1'
#70000
0'
#75000
b11 1
1'
#80000
0'
#85000
b1 3
1!
b0 1
1'
#90000
0'
#95000
b1 1
1'
#100000
0'
#105000
b10 1
1'
#110000
0'
#115000
b11 1
1'
#120000
0'
#125000
b1 -
b10011010 *
0#
b1100100 4
b1 0
0!
b0 1
1'
#130000
0'
#135000
b1 1
1'
#140000
0'
#145000
b10 1
1'
#150000
0'
#155000
b11 1
1'
#160000
0'
#165000
b11 3
1!
b0 1
1'
#170000
0'
#175000
b1 1
1'
#180000
0'
#185000
b10 1
1'
#190000
0'
#195000
b11 1
1'
#200000
0'
#205000
b10 -
0(
b110100 *
1#
b11001000 4
b10 0
0!
b0 1
1'
#210000
0'
#215000
b1 1
1'
#220000
0'
#225000
b10 1
1'
#230000
0'
#235000
b11 1
1'
#240000
0'
#245000
b110 3
1!
b0 1
1'
#250000
0'
#255000
b1 1
1'
#260000
0'
#265000
b10 1
1'
#270000
0'
#275000
b11 1
1'
#280000
0'
#285000
b11 -
b1101000 *
b10010000 4
b11 0
0!
b0 1
1'
#290000
0'
#295000
b1 1
1'
#300000
0'
#305000
b10 1
1'
#310000
0'
#315000
b11 1
1'
#320000
0'
#325000
b1100 3
1!
b0 1
1'
#330000
0'
#335000
b1 1
1'
#340000
0'
#345000
b10 1
1'
#350000
0'
#355000
b11 1
1'
#360000
0'
#365000
b100 -
1(
b11010000 *
0#
b100000 4
b100 0
0!
b0 1
1'
#370000
0'
#375000
b1 1
1'
#380000
0'
#385000
b10 1
1'
#390000
0'
#395000
b11 1
1'
#400000
0'
#405000
b11001 3
1!
b0 1
1'
#410000
0'
#415000
b1 1
1'
#420000
0'
#425000
b10 1
1'
#430000
0'
#435000
b11 1
1'
#440000
0'
#445000
b101 -
b10100000 *
b1000000 4
b101 0
0!
b0 1
1'
#450000
0'
#455000
b1 1
1'
#460000
0'
#465000
b10 1
1'
#470000
0'
#475000
b11 1
1'
#480000
0'
#485000
b110011 3
1!
b0 1
1'
#490000
0'
#495000
b1 1
1'
#500000
0'
#505000
b10 1
1'
#510000
0'
#515000
b11 1
1'
#520000
0'
#525000
b110 -
0(
b1000000 *
1#
b10000000 4
b110 0
0!
b0 1
1'
#530000
0'
#535000
b1 1
1'
#540000
0'
#545000
b10 1
1'
#550000
0'
#555000
b11 1
1'
#560000
0'
#565000
b1100110 3
1!
b0 1
1'
#570000
0'
#575000
b1 1
1'
#580000
0'
#585000
b10 1
1'
#590000
0'
#595000
b11 1
1'
#600000
0'
#605000
b111 -
1(
b10000000 *
0#
b0 4
b111 0
0!
b0 1
1'
#610000
0'
#615000
b1 1
1'
#620000
0'
#625000
b10 1
1'
#630000
0'
#635000
b11 1
1'
#640000
0'
#645000
b11001101 3
1!
b0 1
1'
#650000
0'
#655000
b1 1
1'
#660000
0'
#665000
b10 1
1'
#670000
0'
#675000
b11 1
1'
#680000
0'
#685000
1%
1$
0&
b11001101 "
b11001101 2
0!
b0 1
1'
#690000
0'
#695000
0$
1'
